MANIFEST.in
README.md
setup.py
./etcdlock/__init__.py
./etcdlock/lock.py
etcdlock/__init__.py
etcdlock/lock.py
python_etcd_lock.egg-info/PKG-INFO
python_etcd_lock.egg-info/SOURCES.txt
python_etcd_lock.egg-info/dependency_links.txt
python_etcd_lock.egg-info/not-zip-safe
python_etcd_lock.egg-info/requires.txt
python_etcd_lock.egg-info/top_level.txt