Metadata-Version: 1.1
Name: python-etcd-lock
Version: 0.0.4
Summary: A distributed lock recipe for etcd
Home-page: https://github.com/appuri/python-etcd-lock
Author: Nathan Black
Author-email: nathan@appuri.com
License: ISC
Keywords: etcd distributed lock semaphore mutex
Platform: UNKNOWN
Classifier: Topic :: System :: Distributed Computing
Classifier: Topic :: Software Development :: Libraries
Classifier: License :: OSI Approved :: ISC License (ISCL)
Classifier: Programming Language :: Python :: 2
Classifier: Programming Language :: Python :: 3
Classifier: Topic :: Database :: Front-Ends
